{
  "name": "Milipol Asia-Pacific 2026",
  "series": "Milipol Asia-Pacific",
  "edition": "2026",
  "alias": [
    "Milipol TechX 2026",
    "MTX 2026"
  ],
  "startDate": "2026-04-28",
  "endDate": "2026-04-30",
  "website": "https://www.milipolasiapacific.com",
  "social": [
    {
      "platform": "linkedin",
      "url": "https://www.linkedin.com/company/milipol-asia-pacific"
    }
  ],
  "organiser": [
    {
      "name": "Comexposium Singapore"
    },
    {
      "name": "Milipol"
    }
  ],
  "exhibitorListUrl": "https://mtx26.mapyourshow.com/8_0/floorplan/index.cfm?hallD=A&level=1&hallID=A&st=exhibitor",
  "exhibitorListDate": "2026-03-10T13:40:59+00:00",
  "exhibitor": [
    {
      "name": "ACCENTURE",
      "exhibitorUrl": "https://mtx26.mapyourshow.com/8_0/exhibitor/exhibitor-details.cfm?exhid=L1-L09"
    },
    {
      "name": "ACCUEIL & STREAMWIDE",
      "exhibitorUrl": "https://mtx26.mapyourshow.com/8_0/exhibitor/exhibitor-details.cfm?exhid=L1-Q22"
    },
    {
      "name": "ACE6 TECHNOLOGY PTE LTD",
      "exhibitorUrl": "https://mtx26.mapyourshow.com/8_0/exhibitor/exhibitor-details.cfm?exhid=L1-A21"
    },
    {
      "name": "ADAPTIVE SYSTEMS PTE LTD",
      "exhibitorUrl": "https://mtx26.mapyourshow.com/8_0/exhibitor/exhibitor-details.cfm?exhid=L1-B22"
    },
    {
      "name": "ADDER TECHNOLOGY (ASIA PACIFIC) PTE LTD",
      "exhibitorUrl": "https://mtx26.mapyourshow.com/8_0/exhibitor/exhibitor-details.cfm?exhid=L1-E23"
    },
    {
      "name": "ADOBE",
      "exhibitorUrl": "https://mtx26.mapyourshow.com/8_0/exhibitor/exhibitor-details.cfm?exhid=L1-P13"
    },
    {
      "name": "AEQON TJ PTE LTD",
      "exhibitorUrl": "https://mtx26.mapyourshow.com/8_0/exhibitor/exhibitor-details.cfm?exhid=L1-C09"
    },
    {
      "name": "AETOS",
      "exhibitorUrl": "https://mtx26.mapyourshow.com/8_0/exhibitor/exhibitor-details.cfm?exhid=L1-L22"
    },
    {
      "name": "AG GROUP 007",
      "exhibitorUrl": "https://mtx26.mapyourshow.com/8_0/exhibitor/exhibitor-details.cfm?exhid=L1-T13"
    },
    {
      "name": "ALLIED VISION",
      "exhibitorUrl": "https://mtx26.mapyourshow.com/8_0/exhibitor/exhibitor-details.cfm?exhid=L1-T11"
    },
    {
      "name": "AQUILA DEEP INTEL",
      "exhibitorUrl": "https://mtx26.mapyourshow.com/8_0/exhibitor/exhibitor-details.cfm?exhid=L1-Q18"
    },
    {
      "name": "AREA SPA",
      "exhibitorUrl": "https://mtx26.mapyourshow.com/8_0/exhibitor/exhibitor-details.cfm?exhid=L1-S11"
    },
    {
      "name": "ARMEDGE PTE LTD",
      "exhibitorUrl": "https://mtx26.mapyourshow.com/8_0/exhibitor/exhibitor-details.cfm?exhid=L1-F23"
    },
    {
      "name": "ASME",
      "exhibitorUrl": "https://mtx26.mapyourshow.com/8_0/exhibitor/exhibitor-details.cfm?exhid=L1-A22"
    },
    {
      "name": "ASSET (Advanced ICT Security Systems & Equipment Trading)",
      "exhibitorUrl": "https://mtx26.mapyourshow.com/8_0/exhibitor/exhibitor-details.cfm?exhid=L1-R01"
    },
    {
      "name": "ASSOCIATION",
      "exhibitorUrl": "https://mtx26.mapyourshow.com/8_0/exhibitor/exhibitor-details.cfm?exhid=ASSOCIATION"
    },
    {
      "name": "ASTROPHYSICS",
      "exhibitorUrl": "https://mtx26.mapyourshow.com/8_0/exhibitor/exhibitor-details.cfm?exhid=L1-Q14"
    },
    {
      "name": "AXON",
      "exhibitorUrl": "https://mtx26.mapyourshow.com/8_0/exhibitor/exhibitor-details.cfm?exhid=L1-S17"
    },
    {
      "name": "BAE INTELLIGENCE",
      "exhibitorUrl": "https://mtx26.mapyourshow.com/8_0/exhibitor/exhibitor-details.cfm?exhid=L1-T25"
    },
    {
      "name": "BEIJING GSAFETY",
      "exhibitorUrl": "https://mtx26.mapyourshow.com/8_0/exhibitor/exhibitor-details.cfm?exhid=L1-E17"
    },
    {
      "name": "BLACKSCORE PTE LTD",
      "exhibitorUrl": "https://mtx26.mapyourshow.com/8_0/exhibitor/exhibitor-details.cfm?exhid=LD-D06"
    },
    {
      "name": "BLU5 VIEW PTE LTD",
      "exhibitorUrl": "https://mtx26.mapyourshow.com/8_0/exhibitor/exhibitor-details.cfm?exhid=L1-B23"
    },
    {
      "name": "CELLEBRITE",
      "exhibitorUrl": "https://mtx26.mapyourshow.com/8_0/exhibitor/exhibitor-details.cfm?exhid=L1-L17"
    },
    {
      "name": "CERTIS",
      "exhibitorUrl": "https://mtx26.mapyourshow.com/8_0/exhibitor/exhibitor-details.cfm?exhid=L1-K17"
    },
    {
      "name": "CHECKPOINT",
      "exhibitorUrl": "https://mtx26.mapyourshow.com/8_0/exhibitor/exhibitor-details.cfm?exhid=L1-M17"
    },
    {
      "name": "CISCO",
      "exhibitorUrl": "https://mtx26.mapyourshow.com/8_0/exhibitor/exhibitor-details.cfm?exhid=L1-L07"
    },
    {
      "name": "CLEARTRAIL TECHNOLOGIES",
      "exhibitorUrl": "https://mtx26.mapyourshow.com/8_0/exhibitor/exhibitor-details.cfm?exhid=L1-T07"
    },
    {
      "name": "COGNYTE",
      "exhibitorUrl": "https://mtx26.mapyourshow.com/8_0/exhibitor/exhibitor-details.cfm?exhid=L1-R07"
    },
    {
      "name": "CONTEGO AI",
      "exhibitorUrl": "https://mtx26.mapyourshow.com/8_0/exhibitor/exhibitor-details.cfm?exhid=L1-V02"
    },
    {
      "name": "CORNERSTONE TECHNICA PTE LTD",
      "exhibitorUrl": "https://mtx26.mapyourshow.com/8_0/exhibitor/exhibitor-details.cfm?exhid=L1-C13"
    },
    {
      "name": "COVENTRY ENTERPRISE SINGAPORE",
      "exhibitorUrl": "https://mtx26.mapyourshow.com/8_0/exhibitor/exhibitor-details.cfm?exhid=L1-E24"
    },
    {
      "name": "CYABRA",
      "exhibitorUrl": "https://mtx26.mapyourshow.com/8_0/exhibitor/exhibitor-details.cfm?exhid=L1-R18"
    },
    {
      "name": "CYBERARK",
      "exhibitorUrl": "https://mtx26.mapyourshow.com/8_0/exhibitor/exhibitor-details.cfm?exhid=L1-P18"
    },
    {
      "name": "CYBERGLOBES",
      "exhibitorUrl": "https://mtx26.mapyourshow.com/8_0/exhibitor/exhibitor-details.cfm?exhid=L1-Q25"
    },
    {
      "name": "D-FEND SOLUTIONS",
      "exhibitorUrl": "https://mtx26.mapyourshow.com/8_0/exhibitor/exhibitor-details.cfm?exhid=L1-T15"
    },
    {
      "name": "D-RON SINGAPORE PTE LTD",
      "exhibitorUrl": "https://mtx26.mapyourshow.com/8_0/exhibitor/exhibitor-details.cfm?exhid=L1-B15"
    },
    {
      "name": "DATA EXPERT",
      "exhibitorUrl": "https://mtx26.mapyourshow.com/8_0/exhibitor/exhibitor-details.cfm?exhid=L1-U24"
    },
    {
      "name": "DATA PILOT",
      "exhibitorUrl": "https://mtx26.mapyourshow.com/8_0/exhibitor/exhibitor-details.cfm?exhid=L1-R24"
    },
    {
      "name": "DELAIR SAS",
      "exhibitorUrl": "https://mtx26.mapyourshow.com/8_0/exhibitor/exhibitor-details.cfm?exhid=L1-Q17"
    },
    {
      "name": "DELL",
      "exhibitorUrl": "https://mtx26.mapyourshow.com/8_0/exhibitor/exhibitor-details.cfm?exhid=L1-F01"
    },
    {
      "name": "DOMO TACTICAL COMMUNICATIONS (DTC)",
      "exhibitorUrl": "https://mtx26.mapyourshow.com/8_0/exhibitor/exhibitor-details.cfm?exhid=L1-Q09"
    },
    {
      "name": "DRAGO / PARABOT",
      "exhibitorUrl": "https://mtx26.mapyourshow.com/8_0/exhibitor/exhibitor-details.cfm?exhid=L1-Q16"
    },
    {
      "name": "DRONE SENSE AI",
      "exhibitorUrl": "https://mtx26.mapyourshow.com/8_0/exhibitor/exhibitor-details.cfm?exhid=L1-U22"
    },
    {
      "name": "DXC",
      "exhibitorUrl": "https://mtx26.mapyourshow.com/8_0/exhibitor/exhibitor-details.cfm?exhid=L1-F15"
    },
    {
      "name": "EAST GEAR INTERNATIONAL",
      "exhibitorUrl": "https://mtx26.mapyourshow.com/8_0/exhibitor/exhibitor-details.cfm?exhid=L1-T17"
    },
    {
      "name": "ELASTICSEARCH",
      "exhibitorUrl": "https://mtx26.mapyourshow.com/8_0/exhibitor/exhibitor-details.cfm?exhid=L1-P23"
    },
    {
      "name": "ELBIT",
      "exhibitorUrl": "https://mtx26.mapyourshow.com/8_0/exhibitor/exhibitor-details.cfm?exhid=L1-U16"
    },
    {
      "name": "ELEPHANTASTIC",
      "exhibitorUrl": "https://mtx26.mapyourshow.com/8_0/exhibitor/exhibitor-details.cfm?exhid=L1-T24"
    },
    {
      "name": "ERNST & YOUNG",
      "exhibitorUrl": "https://mtx26.mapyourshow.com/8_0/exhibitor/exhibitor-details.cfm?exhid=L1-M14"
    },
    {
      "name": "ESCALAR",
      "exhibitorUrl": "https://mtx26.mapyourshow.com/8_0/exhibitor/exhibitor-details.cfm?exhid=L1-E10"
    },
    {
      "name": "ESPY",
      "exhibitorUrl": "https://mtx26.mapyourshow.com/8_0/exhibitor/exhibitor-details.cfm?exhid=L1-U20"
    },
    {
      "name": "ESRI",
      "exhibitorUrl": "https://mtx26.mapyourshow.com/8_0/exhibitor/exhibitor-details.cfm?exhid=L1-Q07"
    },
    {
      "name": "F5 NETWORK",
      "exhibitorUrl": "https://mtx26.mapyourshow.com/8_0/exhibitor/exhibitor-details.cfm?exhid=L1-P22"
    },
    {
      "name": "FALKOR",
      "exhibitorUrl": "https://mtx26.mapyourshow.com/8_0/exhibitor/exhibitor-details.cfm?exhid=L1-R12"
    },
    {
      "name": "FIOCCHI MUNIZIONI S.p.A.",
      "exhibitorUrl": "https://mtx26.mapyourshow.com/8_0/exhibitor/exhibitor-details.cfm?exhid=L1-S13"
    },
    {
      "name": "FORENSCOPE",
      "exhibitorUrl": "https://mtx26.mapyourshow.com/8_0/exhibitor/exhibitor-details.cfm?exhid=L1-S23"
    },
    {
      "name": "FORTINET",
      "exhibitorUrl": "https://mtx26.mapyourshow.com/8_0/exhibitor/exhibitor-details.cfm?exhid=L1-E01"
    },
    {
      "name": "FUNZIN CO.",
      "exhibitorUrl": "https://mtx26.mapyourshow.com/8_0/exhibitor/exhibitor-details.cfm?exhid=L1-W03"
    },
    {
      "name": "GEDION",
      "exhibitorUrl": "https://mtx26.mapyourshow.com/8_0/exhibitor/exhibitor-details.cfm?exhid=L1-U13"
    },
    {
      "name": "GLAMCO",
      "exhibitorUrl": "https://mtx26.mapyourshow.com/8_0/exhibitor/exhibitor-details.cfm?exhid=L1-E16"
    },
    {
      "name": "GLOBAL SECURITY & SURVEILLANCE",
      "exhibitorUrl": "https://mtx26.mapyourshow.com/8_0/exhibitor/exhibitor-details.cfm?exhid=L1-A23"
    },
    {
      "name": "GRIPID",
      "exhibitorUrl": "https://mtx26.mapyourshow.com/8_0/exhibitor/exhibitor-details.cfm?exhid=L1-Q21"
    },
    {
      "name": "HAROGIC TECH",
      "exhibitorUrl": "https://mtx26.mapyourshow.com/8_0/exhibitor/exhibitor-details.cfm?exhid=L1-C10"
    },
    {
      "name": "HENSOLDT",
      "exhibitorUrl": "https://mtx26.mapyourshow.com/8_0/exhibitor/exhibitor-details.cfm?exhid=L1-E13"
    },
    {
      "name": "HGH SYSTEMES INFRAROUGES",
      "exhibitorUrl": "https://mtx26.mapyourshow.com/8_0/exhibitor/exhibitor-details.cfm?exhid=L1-Q19"
    },
    {
      "name": "HID",
      "exhibitorUrl": "https://mtx26.mapyourshow.com/8_0/exhibitor/exhibitor-details.cfm?exhid=L1-U06"
    },
    {
      "name": "HIKVISION",
      "exhibitorUrl": "https://mtx26.mapyourshow.com/8_0/exhibitor/exhibitor-details.cfm?exhid=L1-J21"
    },
    {
      "name": "HPE",
      "exhibitorUrl": "https://mtx26.mapyourshow.com/8_0/exhibitor/exhibitor-details.cfm?exhid=L1-L01"
    },
    {
      "name": "HTX CYBER ZONE",
      "exhibitorUrl": "https://mtx26.mapyourshow.com/8_0/exhibitor/exhibitor-details.cfm?exhid=L1-002"
    },
    {
      "name": "HTX Central Zone",
      "exhibitorUrl": "https://mtx26.mapyourshow.com/8_0/exhibitor/exhibitor-details.cfm?exhid=L1-001"
    },
    {
      "name": "HTX DEVELOPER ZONE",
      "exhibitorUrl": "https://mtx26.mapyourshow.com/8_0/exhibitor/exhibitor-details.cfm?exhid=L1-003"
    },
    {
      "name": "HTX ROBOTICS ZONE",
      "exhibitorUrl": "https://mtx26.mapyourshow.com/8_0/exhibitor/exhibitor-details.cfm?exhid=L1-005"
    },
    {
      "name": "HTX SCIENCE ZONE",
      "exhibitorUrl": "https://mtx26.mapyourshow.com/8_0/exhibitor/exhibitor-details.cfm?exhid=L1-004"
    },
    {
      "name": "IAI",
      "exhibitorUrl": "https://mtx26.mapyourshow.com/8_0/exhibitor/exhibitor-details.cfm?exhid=L1-M21"
    },
    {
      "name": "IBM",
      "exhibitorUrl": "https://mtx26.mapyourshow.com/8_0/exhibitor/exhibitor-details.cfm?exhid=L1-M15"
    },
    {
      "name": "IDEMIA",
      "exhibitorUrl": "https://mtx26.mapyourshow.com/8_0/exhibitor/exhibitor-details.cfm?exhid=L1-G17"
    },
    {
      "name": "ILUMINA",
      "exhibitorUrl": "https://mtx26.mapyourshow.com/8_0/exhibitor/exhibitor-details.cfm?exhid=L1-E20"
    },
    {
      "name": "INSIG2 LTD",
      "exhibitorUrl": "https://mtx26.mapyourshow.com/8_0/exhibitor/exhibitor-details.cfm?exhid=L1-S26"
    },
    {
      "name": "INTERIONET",
      "exhibitorUrl": "https://mtx26.mapyourshow.com/8_0/exhibitor/exhibitor-details.cfm?exhid=L1-R13"
    },
    {
      "name": "IP-TRIBE",
      "exhibitorUrl": "https://mtx26.mapyourshow.com/8_0/exhibitor/exhibitor-details.cfm?exhid=L1-K25"
    },
    {
      "name": "IPS SECUREX PTE LTD",
      "exhibitorUrl": "https://mtx26.mapyourshow.com/8_0/exhibitor/exhibitor-details.cfm?exhid=L1-A09"
    },
    {
      "name": "Innova S.p.A",
      "exhibitorUrl": "https://mtx26.mapyourshow.com/8_0/exhibitor/exhibitor-details.cfm?exhid=L1-S12"
    },
    {
      "name": "JSI",
      "exhibitorUrl": "https://mtx26.mapyourshow.com/8_0/exhibitor/exhibitor-details.cfm?exhid=L1-T26"
    },
    {
      "name": "KAISER-SGI ASIA PTE LTD",
      "exhibitorUrl": "https://mtx26.mapyourshow.com/8_0/exhibitor/exhibitor-details.cfm?exhid=L1-C15"
    },
    {
      "name": "KALLMAN",
      "exhibitorUrl": "https://mtx26.mapyourshow.com/8_0/exhibitor/exhibitor-details.cfm?exhid=L1-Q10"
    },
    {
      "name": "KENKO TOKINA",
      "exhibitorUrl": "https://mtx26.mapyourshow.com/8_0/exhibitor/exhibitor-details.cfm?exhid=L1-U26"
    },
    {
      "name": "KLASS",
      "exhibitorUrl": "https://mtx26.mapyourshow.com/8_0/exhibitor/exhibitor-details.cfm?exhid=L1-E07"
    },
    {
      "name": "KNOVEL",
      "exhibitorUrl": "https://mtx26.mapyourshow.com/8_0/exhibitor/exhibitor-details.cfm?exhid=L1-J17"
    },
    {
      "name": "KOMANDO IMMERSIF INDONESIA",
      "exhibitorUrl": "https://mtx26.mapyourshow.com/8_0/exhibitor/exhibitor-details.cfm?exhid=L1-T14"
    },
    {
      "name": "L1-REST LOUNGE AND COFFEE CART",
      "exhibitorUrl": "https://mtx26.mapyourshow.com/8_0/exhibitor/exhibitor-details.cfm?exhid=L1"
    },
    {
      "name": "LPS LENOVO",
      "exhibitorUrl": "https://mtx26.mapyourshow.com/8_0/exhibitor/exhibitor-details.cfm?exhid=L1-M01"
    },
    {
      "name": "LUFRACOM GmBH",
      "exhibitorUrl": "https://mtx26.mapyourshow.com/8_0/exhibitor/exhibitor-details.cfm?exhid=L1-U14"
    },
    {
      "name": "MAGNET FORENSICS",
      "exhibitorUrl": "https://mtx26.mapyourshow.com/8_0/exhibitor/exhibitor-details.cfm?exhid=L1-P27"
    },
    {
      "name": "MARIS TECH",
      "exhibitorUrl": "https://mtx26.mapyourshow.com/8_0/exhibitor/exhibitor-details.cfm?exhid=L1-R15"
    },
    {
      "name": "MH SERVICE",
      "exhibitorUrl": "https://mtx26.mapyourshow.com/8_0/exhibitor/exhibitor-details.cfm?exhid=L1-T18"
    },
    {
      "name": "MILIPOL NETWORK",
      "exhibitorUrl": "https://mtx26.mapyourshow.com/8_0/exhibitor/exhibitor-details.cfm?exhid=MILIPOL_NETWORK"
    },
    {
      "name": "MISTRAL AI",
      "exhibitorUrl": "https://mtx26.mapyourshow.com/8_0/exhibitor/exhibitor-details.cfm?exhid=L1-N14"
    },
    {
      "name": "MKU LIMITED",
      "exhibitorUrl": "https://mtx26.mapyourshow.com/8_0/exhibitor/exhibitor-details.cfm?exhid=L1-T12"
    },
    {
      "name": "MOODY'S ANALYTICS",
      "exhibitorUrl": "https://mtx26.mapyourshow.com/8_0/exhibitor/exhibitor-details.cfm?exhid=L1-L28"
    },
    {
      "name": "MOTOROLA SOLUTIONS SINGAPORE PTE LTD",
      "exhibitorUrl": "https://mtx26.mapyourshow.com/8_0/exhibitor/exhibitor-details.cfm?exhid=L1-R19"
    },
    {
      "name": "MSAB",
      "exhibitorUrl": "https://mtx26.mapyourshow.com/8_0/exhibitor/exhibitor-details.cfm?exhid=L1-T23"
    },
    {
      "name": "Mehler Protection",
      "exhibitorUrl": "https://mtx26.mapyourshow.com/8_0/exhibitor/exhibitor-details.cfm?exhid=L1-U12"
    },
    {
      "name": "NCS",
      "exhibitorUrl": "https://mtx26.mapyourshow.com/8_0/exhibitor/exhibitor-details.cfm?exhid=L1-G07"
    },
    {
      "name": "NEC",
      "exhibitorUrl": "https://mtx26.mapyourshow.com/8_0/exhibitor/exhibitor-details.cfm?exhid=L1-J01"
    },
    {
      "name": "NITECORE",
      "exhibitorUrl": "https://mtx26.mapyourshow.com/8_0/exhibitor/exhibitor-details.cfm?exhid=L1-Y05"
    },
    {
      "name": "NOVATECH RESOURCES PTE LTD",
      "exhibitorUrl": "https://mtx26.mapyourshow.com/8_0/exhibitor/exhibitor-details.cfm?exhid=L1-C08"
    },
    {
      "name": "NOVO DR",
      "exhibitorUrl": "https://mtx26.mapyourshow.com/8_0/exhibitor/exhibitor-details.cfm?exhid=L1-R23"
    },
    {
      "name": "NTT",
      "exhibitorUrl": "https://mtx26.mapyourshow.com/8_0/exhibitor/exhibitor-details.cfm?exhid=L1-N20"
    },
    {
      "name": "NUCTECH",
      "exhibitorUrl": "https://mtx26.mapyourshow.com/8_0/exhibitor/exhibitor-details.cfm?exhid=L1-Y01"
    },
    {
      "name": "NUTANIX",
      "exhibitorUrl": "https://mtx26.mapyourshow.com/8_0/exhibitor/exhibitor-details.cfm?exhid=L1-M07"
    },
    {
      "name": "OMNI INTEGER PTE LTD",
      "exhibitorUrl": "https://mtx26.mapyourshow.com/8_0/exhibitor/exhibitor-details.cfm?exhid=L1-B13"
    },
    {
      "name": "OVATION SYSTEMS",
      "exhibitorUrl": "https://mtx26.mapyourshow.com/8_0/exhibitor/exhibitor-details.cfm?exhid=L1-T22"
    },
    {
      "name": "PALO ALTO",
      "exhibitorUrl": "https://mtx26.mapyourshow.com/8_0/exhibitor/exhibitor-details.cfm?exhid=L1-N01"
    },
    {
      "name": "PCSS",
      "exhibitorUrl": "https://mtx26.mapyourshow.com/8_0/exhibitor/exhibitor-details.cfm?exhid=L1-H01"
    },
    {
      "name": "PERFORM ROTORS",
      "exhibitorUrl": "https://mtx26.mapyourshow.com/8_0/exhibitor/exhibitor-details.cfm?exhid=L1-S20"
    },
    {
      "name": "PRECISION FABRICATORS PTE LTD",
      "exhibitorUrl": "https://mtx26.mapyourshow.com/8_0/exhibitor/exhibitor-details.cfm?exhid=L1-C24"
    },
    {
      "name": "PRECISION TECHNOLOGIES",
      "exhibitorUrl": "https://mtx26.mapyourshow.com/8_0/exhibitor/exhibitor-details.cfm?exhid=LD-D12"
    },
    {
      "name": "PROENGIN",
      "exhibitorUrl": "https://mtx26.mapyourshow.com/8_0/exhibitor/exhibitor-details.cfm?exhid=L1-Q20"
    },
    {
      "name": "PROJECTINA",
      "exhibitorUrl": "https://mtx26.mapyourshow.com/8_0/exhibitor/exhibitor-details.cfm?exhid=L1-V04"
    },
    {
      "name": "PURE STORAGE",
      "exhibitorUrl": "https://mtx26.mapyourshow.com/8_0/exhibitor/exhibitor-details.cfm?exhid=L1-P17"
    },
    {
      "name": "QUANTEXA",
      "exhibitorUrl": "https://mtx26.mapyourshow.com/8_0/exhibitor/exhibitor-details.cfm?exhid=L1-M28"
    },
    {
      "name": "RAPISCAN SYSTEMS PTE LTD",
      "exhibitorUrl": "https://mtx26.mapyourshow.com/8_0/exhibitor/exhibitor-details.cfm?exhid=L1-W01"
    },
    {
      "name": "RAYZONE GROUP",
      "exhibitorUrl": "https://mtx26.mapyourshow.com/8_0/exhibitor/exhibitor-details.cfm?exhid=L1-R09"
    },
    {
      "name": "REACH INFORMATION",
      "exhibitorUrl": "https://mtx26.mapyourshow.com/8_0/exhibitor/exhibitor-details.cfm?exhid=L1-W05"
    },
    {
      "name": "RED ALPHA",
      "exhibitorUrl": "https://mtx26.mapyourshow.com/8_0/exhibitor/exhibitor-details.cfm?exhid=L1-P21"
    },
    {
      "name": "RED HAT",
      "exhibitorUrl": "https://mtx26.mapyourshow.com/8_0/exhibitor/exhibitor-details.cfm?exhid=L1-M27"
    },
    {
      "name": "REGULUS CYBER",
      "exhibitorUrl": "https://mtx26.mapyourshow.com/8_0/exhibitor/exhibitor-details.cfm?exhid=L1-R17"
    },
    {
      "name": "RESEARCH ELECTRONICS INTERNATIONAL (REI)",
      "exhibitorUrl": "https://mtx26.mapyourshow.com/8_0/exhibitor/exhibitor-details.cfm?exhid=L1-Q13"
    },
    {
      "name": "ROHDE & SCHWARZ",
      "exhibitorUrl": "https://mtx26.mapyourshow.com/8_0/exhibitor/exhibitor-details.cfm?exhid=L1--K22"
    },
    {
      "name": "RUBYTEK PTE LTD",
      "exhibitorUrl": "https://mtx26.mapyourshow.com/8_0/exhibitor/exhibitor-details.cfm?exhid=LD-D15"
    },
    {
      "name": "RYCA PTE LTD",
      "exhibitorUrl": "https://mtx26.mapyourshow.com/8_0/exhibitor/exhibitor-details.cfm?exhid=LD-D18"
    },
    {
      "name": "S&E CORPORATION PTE LTD",
      "exhibitorUrl": "https://mtx26.mapyourshow.com/8_0/exhibitor/exhibitor-details.cfm?exhid=L1-E25"
    },
    {
      "name": "SAMSUNG",
      "exhibitorUrl": "https://mtx26.mapyourshow.com/8_0/exhibitor/exhibitor-details.cfm?exhid=L1-K01"
    },
    {
      "name": "SAS",
      "exhibitorUrl": "https://mtx26.mapyourshow.com/8_0/exhibitor/exhibitor-details.cfm?exhid=L1-R21"
    },
    {
      "name": "SCHNEIDER ELECTRIC",
      "exhibitorUrl": "https://mtx26.mapyourshow.com/8_0/exhibitor/exhibitor-details.cfm?exhid=L1-L25"
    },
    {
      "name": "SENSAI",
      "exhibitorUrl": "https://mtx26.mapyourshow.com/8_0/exhibitor/exhibitor-details.cfm?exhid=L1-E21"
    },
    {
      "name": "SENSOR MICRO",
      "exhibitorUrl": "https://mtx26.mapyourshow.com/8_0/exhibitor/exhibitor-details.cfm?exhid=L1-Y03"
    },
    {
      "name": "SERB PHARMA",
      "exhibitorUrl": "https://mtx26.mapyourshow.com/8_0/exhibitor/exhibitor-details.cfm?exhid=L1-Q23"
    },
    {
      "name": "SIIX",
      "exhibitorUrl": "https://mtx26.mapyourshow.com/8_0/exhibitor/exhibitor-details.cfm?exhid=L1-E14"
    },
    {
      "name": "SILK EXPRESS FREIGHT PTE LTD",
      "exhibitorUrl": "https://mtx26.mapyourshow.com/8_0/exhibitor/exhibitor-details.cfm?exhid=L1-B21"
    },
    {
      "name": "SINGTEL",
      "exhibitorUrl": "https://mtx26.mapyourshow.com/8_0/exhibitor/exhibitor-details.cfm?exhid=L1-H17"
    },
    {
      "name": "SMITHS DETECT",
      "exhibitorUrl": "https://mtx26.mapyourshow.com/8_0/exhibitor/exhibitor-details.cfm?exhid=L1-T16"
    },
    {
      "name": "ST ENGINEERING",
      "exhibitorUrl": "https://mtx26.mapyourshow.com/8_0/exhibitor/exhibitor-details.cfm?exhid=L1-G01"
    },
    {
      "name": "ST LOGISTICS",
      "exhibitorUrl": "https://mtx26.mapyourshow.com/8_0/exhibitor/exhibitor-details.cfm?exhid=L1-S24"
    },
    {
      "name": "START-UP ZONE",
      "exhibitorUrl": "https://mtx26.mapyourshow.com/8_0/exhibitor/exhibitor-details.cfm?exhid=L1-H21"
    },
    {
      "name": "STRATIGN",
      "exhibitorUrl": "https://mtx26.mapyourshow.com/8_0/exhibitor/exhibitor-details.cfm?exhid=L1-R05"
    },
    {
      "name": "STUV",
      "exhibitorUrl": "https://mtx26.mapyourshow.com/8_0/exhibitor/exhibitor-details.cfm?exhid=L1-U05"
    },
    {
      "name": "SYFT TECHNOLOGIES",
      "exhibitorUrl": "https://mtx26.mapyourshow.com/8_0/exhibitor/exhibitor-details.cfm?exhid=L1-F21"
    },
    {
      "name": "T.A.R Ideal Concept Ltd.",
      "exhibitorUrl": "https://mtx26.mapyourshow.com/8_0/exhibitor/exhibitor-details.cfm?exhid=L1-W04"
    },
    {
      "name": "TALONS LAB",
      "exhibitorUrl": "https://mtx26.mapyourshow.com/8_0/exhibitor/exhibitor-details.cfm?exhid=L1-B09"
    },
    {
      "name": "TELEDYNE E2V",
      "exhibitorUrl": "https://mtx26.mapyourshow.com/8_0/exhibitor/exhibitor-details.cfm?exhid=L1-S25"
    },
    {
      "name": "TELERADIO ENGINEERING",
      "exhibitorUrl": "https://mtx26.mapyourshow.com/8_0/exhibitor/exhibitor-details.cfm?exhid=LD-D05"
    },
    {
      "name": "THERMO FISHER",
      "exhibitorUrl": "https://mtx26.mapyourshow.com/8_0/exhibitor/exhibitor-details.cfm?exhid=L1-E27"
    },
    {
      "name": "THOUGHTWORKS",
      "exhibitorUrl": "https://mtx26.mapyourshow.com/8_0/exhibitor/exhibitor-details.cfm?exhid=L1-P14"
    },
    {
      "name": "TOTAL DEFENSE SOLUTIONS",
      "exhibitorUrl": "https://mtx26.mapyourshow.com/8_0/exhibitor/exhibitor-details.cfm?exhid=L1-F24"
    },
    {
      "name": "TRD",
      "exhibitorUrl": "https://mtx26.mapyourshow.com/8_0/exhibitor/exhibitor-details.cfm?exhid=L1-Q01"
    },
    {
      "name": "TRUSTVERI5 PTE LTD",
      "exhibitorUrl": "https://mtx26.mapyourshow.com/8_0/exhibitor/exhibitor-details.cfm?exhid=L1-C23"
    },
    {
      "name": "TT INNOVATION & TECHNOLOGY",
      "exhibitorUrl": "https://mtx26.mapyourshow.com/8_0/exhibitor/exhibitor-details.cfm?exhid=LD-D07"
    },
    {
      "name": "TULPAR",
      "exhibitorUrl": "https://mtx26.mapyourshow.com/8_0/exhibitor/exhibitor-details.cfm?exhid=L1-B10"
    },
    {
      "name": "UNIVERS",
      "exhibitorUrl": "https://mtx26.mapyourshow.com/8_0/exhibitor/exhibitor-details.cfm?exhid=L1-P28"
    },
    {
      "name": "VAREX IMAGING",
      "exhibitorUrl": "https://mtx26.mapyourshow.com/8_0/exhibitor/exhibitor-details.cfm?exhid=L1-Q08"
    },
    {
      "name": "VASTDATA",
      "exhibitorUrl": "https://mtx26.mapyourshow.com/8_0/exhibitor/exhibitor-details.cfm?exhid=L1-P08"
    },
    {
      "name": "VECTRA",
      "exhibitorUrl": "https://mtx26.mapyourshow.com/8_0/exhibitor/exhibitor-details.cfm?exhid=L1-N22"
    },
    {
      "name": "VEEAM",
      "exhibitorUrl": "https://mtx26.mapyourshow.com/8_0/exhibitor/exhibitor-details.cfm?exhid=L1-P19"
    },
    {
      "name": "VEREDUS",
      "exhibitorUrl": "https://mtx26.mapyourshow.com/8_0/exhibitor/exhibitor-details.cfm?exhid=L1-E18"
    },
    {
      "name": "VIP LOUNGE",
      "exhibitorUrl": "https://mtx26.mapyourshow.com/8_0/exhibitor/exhibitor-details.cfm?exhid=TEMP_23"
    },
    {
      "name": "VISCOY",
      "exhibitorUrl": "https://mtx26.mapyourshow.com/8_0/exhibitor/exhibitor-details.cfm?exhid=LD-D17"
    },
    {
      "name": "VMI SECURITY",
      "exhibitorUrl": "https://mtx26.mapyourshow.com/8_0/exhibitor/exhibitor-details.cfm?exhid=L1-W02"
    },
    {
      "name": "VTT",
      "exhibitorUrl": "https://mtx26.mapyourshow.com/8_0/exhibitor/exhibitor-details.cfm?exhid=L1-T21"
    },
    {
      "name": "Visage",
      "exhibitorUrl": "https://mtx26.mapyourshow.com/8_0/exhibitor/exhibitor-details.cfm?exhid=L1-S19"
    },
    {
      "name": "WAVE GUARD TECHNOLOGIES LTD",
      "exhibitorUrl": "https://mtx26.mapyourshow.com/8_0/exhibitor/exhibitor-details.cfm?exhid=L1-R14"
    },
    {
      "name": "WEKA",
      "exhibitorUrl": "https://mtx26.mapyourshow.com/8_0/exhibitor/exhibitor-details.cfm?exhid=L1-P01"
    },
    {
      "name": "WEY TECHNOLOGY",
      "exhibitorUrl": "https://mtx26.mapyourshow.com/8_0/exhibitor/exhibitor-details.cfm?exhid=LD-D11"
    },
    {
      "name": "X-RAY CENTER",
      "exhibitorUrl": "https://mtx26.mapyourshow.com/8_0/exhibitor/exhibitor-details.cfm?exhid=L1-U01"
    },
    {
      "name": "ZAP BUILD",
      "exhibitorUrl": "https://mtx26.mapyourshow.com/8_0/exhibitor/exhibitor-details.cfm?exhid=L1-U11"
    }
  ]
}
